{
  "category": "B1",
  "date": "20251101",
  "pts": [
    {
      "no": "5",
      "nameJp": "マット・ボンズ",
      "min": "30:13",
      "pts": 31,
      "f2m": 9,
      "f2a": 15,
      "f3m": 2,
      "f3a": 7,
      "ftm": 7,
      "fta": 8,
      "oreb": 4,
      "dreb": 11,
      "reb": 15,
      "ast": 2,
      "tov": 2,
      "stl": 0,
      "blk": 0,
      "pf": 0,
      "isStarter": true,
      "detailUrl": "https://www.bleague.jp/roster_detail/?PlayerID=26886",
      "name": "MATT BONDS",
      "teamNameRaw": "大阪エヴェッサ",
      "gameId": "504878",
      "cardPath": "output/Bplayers/B1/251101/game_504878_大阪エヴェッサ_レバンガ北海道_20251101/大阪エヴェッサ_5_MATT_BONDS_20251101.png"
    },
    {
      "teamNameRaw": "宇都宮ブレックス",
      "no": "25",
      "isStarter": true,
      "nameJp": "D.J・ニュービル",
      "detailUrl": "https://www.bleague.jp/roster_detail/?PlayerID=33085",
      "min": "34:25",
      "pts": 31,
      "fg2Str": "5/6",
      "fg2Pct": "83.3",
      "fg3Str": "7/13",
      "fg3Pct": "53.8",
      "ftStr": "0/3",
      "ftPct": "0.0",
      "ptsRatio2P": "32",
      "ptsRatio3P": "68",
      "ptsRatioFT": "0",
      "attRatio2P": "32",
      "attRatio3P": "68",
      "reb": 6,
      "oreb": "0",
      "dreb": "6",
      "ast": 7,
      "stl": "0",
      "blk": "0",
      "to": "2",
      "pf": "2",
      "plusMinus": "11",
      "name": "D.J. NEWBILL",
      "gameId": "504862",
      "cardPath": "output/Bplayers/B1/251101/game_504862_宇都宮ブレックス_ファイティングイーグルス名古屋_20251101/宇都宮ブレックス_25_D.J._NEWBILL_20251101.png"
    },
    {
      "no": "8",
      "nameJp": "ジャレット・カルバー",
      "min": "31:21",
      "pts": 28,
      "f2m": 6,
      "f2a": 11,
      "f3m": 3,
      "f3a": 7,
      "ftm": 7,
      "fta": 9,
      "oreb": 1,
      "dreb": 6,
      "reb": 7,
      "ast": 3,
      "tov": 3,
      "stl": 2,
      "blk": 0,
      "pf": 4,
      "isStarter": true,
      "detailUrl": "https://www.bleague.jp/roster_detail/?PlayerID=51000531",
      "name": "JARRETT CULVER",
      "teamNameRaw": "仙台89ERS",
      "gameId": "504858",
      "cardPath": "output/Bplayers/B1/251101/game_504858_仙台89ERS_サンロッカーズ渋谷_20251101/仙台89ERS_8_JARRETT_CULVER_20251101.png"
    },
    {
      "no": "45",
      "nameJp": "セクー・ドゥムブヤ",
      "min": "27:56",
      "pts": 28,
      "f2m": 9,
      "f2a": 14,
      "f3m": 3,
      "f3a": 7,
      "ftm": 1,
      "fta": 2,
      "oreb": 1,
      "dreb": 8,
      "reb": 9,
      "ast": 0,
      "tov": 6,
      "stl": 0,
      "blk": 0,
      "pf": 2,
      "isStarter": true,
      "detailUrl": "https://www.bleague.jp/roster_detail/?PlayerID=51000511",
      "name": "SEKOU DOUMBOUYA",
      "teamNameRaw": "越谷アルファーズ",
      "gameId": "504866",
      "cardPath": "output/Bplayers/B1/251101/game_504866_越谷アルファーズ_琉球ゴールデンキングス_20251101/越谷アルファーズ_45_SEKOU_DOUMBOUYA_20251101.png"
    },
    {
      "no": "5",
      "nameJp": "イ ヒョンジュン",
      "min": "22:50",
      "pts": 28,
      "f2m": 5,
      "f2a": 5,
      "f3m": 6,
      "f3a": 9,
      "ftm": 0,
      "fta": 0,
      "oreb": 1,
      "dreb": 3,
      "reb": 4,
      "ast": 1,
      "tov": 0,
      "stl": 3,
      "blk": 1,
      "pf": 0,
      "isStarter": true,
      "detailUrl": "https://www.bleague.jp/roster_detail/?PlayerID=51000379",
      "name": "HYUNJUNG LEE",
      "teamNameRaw": "長崎ヴェルカ",
      "gameId": "504870",
      "cardPath": "output/Bplayers/B1/251101/game_504870_川崎ブレイブサンダース_長崎ヴェルカ_20251101/長崎ヴェルカ_5_HYUNJUNG_LEE_20251101.png"
    },
    {
      "no": "8",
      "nameJp": "ケリー・ブラックシアー・ジュニア",
      "min": "26:31",
      "pts": 23,
      "f2m": 7,
      "f2a": 8,
      "f3m": 1,
      "f3a": 1,
      "ftm": 6,
      "fta": 6,
      "oreb": 4,
      "dreb": 4,
      "reb": 8,
      "ast": 3,
      "tov": 3,
      "stl": 1,
      "blk": 0,
      "pf": 3,
      "isStarter": true,
      "detailUrl": "https://www.bleague.jp/roster_detail/?PlayerID=51000145",
      "name": "KERRY BLACKSHEARJR",
      "teamNameRaw": "群馬クレインサンダーズ",
      "gameId": "504864",
      "cardPath": "output/Bplayers/B1/251101/game_504864_群馬クレインサンダーズ_横浜ビー・コルセアーズ_20251101/群馬クレインサンダーズ_8_KERRY_BLACKSHEARJR_20251101.png"
    },
    {
      "no": "54",
      "nameJp": "ダバンテ・ガードナー",
      "min": "28:02",
      "pts": 23,
      "f2m": 6,
      "f2a": 8,
      "f3m": 3,
      "f3a": 4,
      "ftm": 2,
      "fta": 2,
      "oreb": 0,
      "dreb": 3,
      "reb": 3,
      "ast": 6,
      "tov": 1,
      "stl": 1,
      "blk": 0,
      "pf": 1,
      "isStarter": true,
      "detailUrl": "https://www.bleague.jp/roster_detail/?PlayerID=9040",
      "name": "DAVANTE GARDNER",
      "teamNameRaw": "シーホース三河",
      "gameId": "504882",
      "cardPath": "output/Bplayers/B1/251101/game_504882_佐賀バルーナーズ_シーホース三河_20251101/シーホース三河_54_DAVANTE_GARDNER_20251101.png"
    },
    {
      "no": "8",
      "nameJp": "トレイ・ケル",
      "min": "26:48",
      "pts": 22,
      "f2m": 6,
      "f2a": 11,
      "f3m": 1,
      "f3a": 4,
      "ftm": 7,
      "fta": 9,
      "oreb": 0,
      "dreb": 7,
      "reb": 7,
      "ast": 3,
      "tov": 2,
      "stl": 1,
      "blk": 0,
      "pf": 3,
      "isStarter": true,
      "detailUrl": "https://www.bleague.jp/roster_detail/?PlayerID=51000524",
      "name": "TREY KELL",
      "teamNameRaw": "富山グラウジーズ",
      "gameId": "504860",
      "cardPath": "output/Bplayers/B1/251101/game_504860_茨城ロボッツ_富山グラウジーズ_20251101/富山グラウジーズ_8_TREY_KELL_20251101.png"
    },
    {
      "no": "9",
      "nameJp": "セルジオ・エル ダーウィッチ",
      "min": "30:35",
      "pts": 21,
      "f2m": 5,
      "f2a": 10,
      "f3m": 2,
      "f3a": 5,
      "ftm": 5,
      "fta": 5,
      "oreb": 0,
      "dreb": 6,
      "reb": 6,
      "ast": 4,
      "tov": 2,
      "stl": 0,
      "blk": 0,
      "pf": 3,
      "isStarter": true,
      "detailUrl": "https://www.bleague.jp/roster_detail/?PlayerID=51000530",
      "name": "SERGIO EL DARWICH",
      "teamNameRaw": "仙台89ERS",
      "gameId": "504858",
      "cardPath": "output/Bplayers/B1/251101/game_504858_仙台89ERS_サンロッカーズ渋谷_20251101/仙台89ERS_9_SERGIO_EL_DARWICH_20251101.png"
    },
    {
      "no": "13",
      "nameJp": "田中 大貴",
      "min": "32:38",
      "pts": 21,
      "f2m": 4,
      "f2a": 6,
      "f3m": 4,
      "f3a": 7,
      "ftm": 1,
      "fta": 1,
      "oreb": 2,
      "dreb": 1,
      "reb": 3,
      "ast": 2,
      "tov": 2,
      "stl": 0,
      "blk": 0,
      "pf": 3,
      "isStarter": true,
      "detailUrl": "https://www.bleague.jp/roster_detail/?PlayerID=9037",
      "name": "DAIKI TANAKA",
      "teamNameRaw": "サンロッカーズ渋谷",
      "gameId": "504858",
      "cardPath": "output/Bplayers/B1/251101/game_504858_仙台89ERS_サンロッカーズ渋谷_20251101/サンロッカーズ渋谷_13_DAIKI_TANAKA_20251101.png"
    }
  ],
  "reb": [
    {
      "teamNameRaw": "ファイティングイーグルス名古屋",
      "no": "54",
      "isStarter": true,
      "nameJp": "ショーン・オマラ",
      "detailUrl": "https://www.bleague.jp/roster_detail/?PlayerID=26912",
      "min": "33:33",
      "pts": 13,
      "fg2Str": "6/15",
      "fg2Pct": "40.0",
      "fg3Str": "0/0",
      "fg3Pct": "0",
      "ftStr": "1/4",
      "ftPct": "25.0",
      "ptsRatio2P": "92",
      "ptsRatio3P": "0",
      "ptsRatioFT": "8",
      "attRatio2P": "100",
      "attRatio3P": "0",
      "reb": 19,
      "oreb": "10",
      "dreb": "9",
      "ast": 4,
      "stl": "0",
      "blk": "1",
      "to": "2",
      "pf": "2",
      "plusMinus": "-7",
      "name": "SEAN OMARA",
      "gameId": "504862",
      "cardPath": "output/Bplayers/B1/251101/game_504862_宇都宮ブレックス_ファイティングイーグルス名古屋_20251101/ファイティングイーグルス名古屋_54_SEAN_OMARA_20251101.png"
    },
    {
      "no": "6",
      "nameJp": "小寺 ハミルトンゲイリー",
      "min": "27:41",
      "pts": 4,
      "f2m": 2,
      "f2a": 5,
      "f3m": 0,
      "f3a": 0,
      "ftm": 0,
      "fta": 0,
      "oreb": 8,
      "dreb": 8,
      "reb": 16,
      "ast": 2,
      "tov": 1,
      "stl": 2,
      "blk": 0,
      "pf": 1,
      "isStarter": true,
      "detailUrl": "https://www.bleague.jp/roster_detail/?PlayerID=9456",
      "name": "HAMILTONGARY KOTERA",
      "teamNameRaw": "越谷アルファーズ",
      "gameId": "504866",
      "cardPath": "output/Bplayers/B1/251101/game_504866_越谷アルファーズ_琉球ゴールデンキングス_20251101/越谷アルファーズ_6_HAMILTONGARY_KOTERA_20251101.png"
    },
    {
      "no": "43",
      "nameJp": "スコット・エサトン",
      "min": "23:55",
      "pts": 11,
      "f2m": 5,
      "f2a": 8,
      "f3m": 0,
      "f3a": 0,
      "ftm": 1,
      "fta": 2,
      "oreb": 7,
      "dreb": 9,
      "reb": 16,
      "ast": 2,
      "tov": 0,
      "stl": 2,
      "blk": 1,
      "pf": 3,
      "isStarter": true,
      "detailUrl": "https://www.bleague.jp/roster_detail/?PlayerID=5100000046",
      "name": "SCOTT EATHERTON",
      "teamNameRaw": "名古屋ダイヤモンドドルフィンズ",
      "gameId": "504872",
      "cardPath": "output/Bplayers/B1/251101/game_504872_名古屋ダイヤモンドドルフィンズ_広島ドラゴンフライズ_20251101/名古屋ダイヤモンドドルフィンズ_43_SCOTT_EATHERTON_20251101.png"
    },
    {
      "no": "33",
      "nameJp": "ジョン・ムーニー",
      "min": "25:22",
      "pts": 11,
      "f2m": 5,
      "f2a": 8,
      "f3m": 0,
      "f3a": 0,
      "ftm": 1,
      "fta": 2,
      "oreb": 5,
      "dreb": 11,
      "reb": 16,
      "ast": 3,
      "tov": 3,
      "stl": 1,
      "blk": 1,
      "pf": 1,
      "isStarter": true,
      "detailUrl": "https://www.bleague.jp/roster_detail/?PlayerID=5100000054",
      "name": "JOHN MOONEY",
      "teamNameRaw": "千葉ジェッツ",
      "gameId": "504868",
      "cardPath": "output/Bplayers/B1/251101/game_504868_アルバルク東京_千葉ジェッツ_20251101/千葉ジェッツ_33_JOHN_MOONEY_20251101.png"
    },
    {
      "no": "5",
      "nameJp": "マット・ボンズ",
      "min": "30:13",
      "pts": 31,
      "f2m": 9,
      "f2a": 15,
      "f3m": 2,
      "f3a": 7,
      "ftm": 7,
      "fta": 8,
      "oreb": 4,
      "dreb": 11,
      "reb": 15,
      "ast": 2,
      "tov": 2,
      "stl": 0,
      "blk": 0,
      "pf": 0,
      "isStarter": true,
      "detailUrl": "https://www.bleague.jp/roster_detail/?PlayerID=26886",
      "name": "MATT BONDS",
      "teamNameRaw": "大阪エヴェッサ",
      "gameId": "504878",
      "cardPath": "output/Bplayers/B1/251101/game_504878_大阪エヴェッサ_レバンガ北海道_20251101/大阪エヴェッサ_5_MATT_BONDS_20251101.png"
    },
    {
      "no": "11",
      "nameJp": "セバスチャン・サイズ",
      "min": "34:09",
      "pts": 21,
      "f2m": 9,
      "f2a": 17,
      "f3m": 0,
      "f3a": 0,
      "ftm": 3,
      "fta": 4,
      "oreb": 7,
      "dreb": 8,
      "reb": 15,
      "ast": 4,
      "tov": 1,
      "stl": 0,
      "blk": 3,
      "pf": 2,
      "isStarter": true,
      "detailUrl": "https://www.bleague.jp/roster_detail/?PlayerID=26921",
      "name": "SEBASTIAN SAIZ",
      "teamNameRaw": "アルバルク東京",
      "gameId": "504868",
      "cardPath": "output/Bplayers/B1/251101/game_504868_アルバルク東京_千葉ジェッツ_20251101/アルバルク東京_11_SEBASTIAN_SAIZ_20251101.png"
    },
    {
      "no": "7",
      "nameJp": "デレク・パードン",
      "min": "30:21",
      "pts": 9,
      "f2m": 2,
      "f2a": 6,
      "f3m": 0,
      "f3a": 1,
      "ftm": 5,
      "fta": 6,
      "oreb": 3,
      "dreb": 9,
      "reb": 12,
      "ast": 1,
      "tov": 4,
      "stl": 1,
      "blk": 1,
      "pf": 0,
      "isStarter": true,
      "detailUrl": "https://www.bleague.jp/roster_detail/?PlayerID=51000321",
      "name": "DERERK PARDON",
      "teamNameRaw": "アルティーリ千葉",
      "gameId": "504880",
      "cardPath": "output/Bplayers/B1/251101/game_504880_島根スサノオマジック_アルティーリ千葉_20251101/アルティーリ千葉_7_DERERK_PARDON_20251101.png"
    },
    {
      "no": "23",
      "nameJp": "コフィ・コーバーン",
      "min": "25:21",
      "pts": 15,
      "f2m": 6,
      "f2a": 11,
      "f3m": 0,
      "f3a": 0,
      "ftm": 3,
      "fta": 5,
      "oreb": 7,
      "dreb": 4,
      "reb": 11,
      "ast": 2,
      "tov": 4,
      "stl": 0,
      "blk": 1,
      "pf": 4,
      "isStarter": true,
      "detailUrl": "https://www.bleague.jp/roster_detail/?PlayerID=51000216",
      "name": "KOFI COCKBURN",
      "teamNameRaw": "広島ドラゴンフライズ",
      "gameId": "504872",
      "cardPath": "output/Bplayers/B1/251101/game_504872_名古屋ダイヤモンドドルフィンズ_広島ドラゴンフライズ_20251101/広島ドラゴンフライズ_23_KOFI_COCKBURN_20251101.png"
    },
    {
      "no": "4",
      "nameJp": "ニック・ケイ",
      "min": "33:20",
      "pts": 15,
      "f2m": 4,
      "f2a": 8,
      "f3m": 2,
      "f3a": 3,
      "ftm": 1,
      "fta": 1,
      "oreb": 4,
      "dreb": 7,
      "reb": 11,
      "ast": 3,
      "tov": 2,
      "stl": 1,
      "blk": 1,
      "pf": 0,
      "isStarter": true,
      "detailUrl": "https://www.bleague.jp/roster_detail/?PlayerID=5100000088",
      "name": "NICK KAY",
      "teamNameRaw": "島根スサノオマジック",
      "gameId": "504880",
      "cardPath": "output/Bplayers/B1/251101/game_504880_島根スサノオマジック_アルティーリ千葉_20251101/島根スサノオマジック_4_NICK_KAY_20251101.png"
    },
    {
      "no": "22",
      "nameJp": "ライアン・ロシター",
      "min": "26:54",
      "pts": 6,
      "f2m": 0,
      "f2a": 2,
      "f3m": 2,
      "f3a": 3,
      "ftm": 0,
      "fta": 0,
      "oreb": 1,
      "dreb": 10,
      "reb": 11,
      "ast": 5,
      "tov": 1,
      "stl": 1,
      "blk": 0,
      "pf": 4,
      "isStarter": true,
      "detailUrl": "https://www.bleague.jp/roster_detail/?PlayerID=8649",
      "name": "RYAN ROSSITER",
      "teamNameRaw": "アルバルク東京",
      "gameId": "504868",
      "cardPath": "output/Bplayers/B1/251101/game_504868_アルバルク東京_千葉ジェッツ_20251101/アルバルク東京_22_RYAN_ROSSITER_20251101.png"
    }
  ],
  "ast": [
    {
      "teamNameRaw": "宇都宮ブレックス",
      "no": "6",
      "isStarter": true,
      "nameJp": "比江島 慎",
      "detailUrl": "https://www.bleague.jp/roster_detail/?PlayerID=8589",
      "min": "27:08",
      "pts": 12,
      "fg2Str": "1/5",
      "fg2Pct": "20.0",
      "fg3Str": "3/4",
      "fg3Pct": "75.0",
      "ftStr": "1/2",
      "ftPct": "50.0",
      "ptsRatio2P": "17",
      "ptsRatio3P": "75",
      "ptsRatioFT": "8",
      "attRatio2P": "56",
      "attRatio3P": "44",
      "reb": 5,
      "oreb": "2",
      "dreb": "3",
      "ast": 9,
      "stl": "1",
      "blk": "0",
      "to": "0",
      "pf": "3",
      "plusMinus": "24",
      "name": "MAKOTO HIEJIMA",
      "gameId": "504862",
      "cardPath": "output/Bplayers/B1/251101/game_504862_宇都宮ブレックス_ファイティングイーグルス名古屋_20251101/宇都宮ブレックス_6_MAKOTO_HIEJIMA_20251101.png"
    },
    {
      "no": "12",
      "nameJp": "小川 麻斗",
      "min": "31:08",
      "pts": 15,
      "f2m": 4,
      "f2a": 11,
      "f3m": 1,
      "f3a": 5,
      "ftm": 4,
      "fta": 4,
      "oreb": 1,
      "dreb": 3,
      "reb": 4,
      "ast": 9,
      "tov": 1,
      "stl": 2,
      "blk": 0,
      "pf": 1,
      "isStarter": true,
      "detailUrl": "https://www.bleague.jp/roster_detail/?PlayerID=5100000033",
      "name": "ASATO OGAWA",
      "teamNameRaw": "京都ハンナリーズ",
      "gameId": "504876",
      "cardPath": "output/Bplayers/B1/251101/game_504876_京都ハンナリーズ_三遠ネオフェニックス_20251101/京都ハンナリーズ_12_ASATO_OGAWA_20251101.png"
    },
    {
      "no": "25",
      "nameJp": "アキル・ミッチェル",
      "min": "25:21",
      "pts": 12,
      "f2m": 3,
      "f2a": 5,
      "f3m": 1,
      "f3a": 3,
      "ftm": 3,
      "fta": 4,
      "oreb": 1,
      "dreb": 6,
      "reb": 7,
      "ast": 9,
      "tov": 1,
      "stl": 1,
      "blk": 0,
      "pf": 1,
      "isStarter": true,
      "detailUrl": "https://www.bleague.jp/roster_detail/?PlayerID=51000395",
      "name": "AKIL MITCHELL",
      "teamNameRaw": "長崎ヴェルカ",
      "gameId": "504870",
      "cardPath": "output/Bplayers/B1/251101/game_504870_川崎ブレイブサンダース_長崎ヴェルカ_20251101/長崎ヴェルカ_25_AKIL_MITCHELL_20251101.png"
    },
    {
      "no": "11",
      "nameJp": "宇都 直輝",
      "min": "26:06",
      "pts": 5,
      "f2m": 1,
      "f2a": 5,
      "f3m": 0,
      "f3a": 2,
      "ftm": 3,
      "fta": 4,
      "oreb": 2,
      "dreb": 5,
      "reb": 7,
      "ast": 8,
      "tov": 2,
      "stl": 1,
      "blk": 1,
      "pf": 1,
      "isStarter": true,
      "detailUrl": "https://www.bleague.jp/roster_detail/?PlayerID=8503",
      "name": "NAOKI UTO",
      "teamNameRaw": "富山グラウジーズ",
      "gameId": "504860",
      "cardPath": "output/Bplayers/B1/251101/game_504860_茨城ロボッツ_富山グラウジーズ_20251101/富山グラウジーズ_11_NAOKI_UTO_20251101.png"
    },
    {
      "no": "7",
      "nameJp": "游 艾喆",
      "min": "23:41",
      "pts": 8,
      "f2m": 1,
      "f2a": 5,
      "f3m": 2,
      "f3a": 3,
      "ftm": 0,
      "fta": 0,
      "oreb": 1,
      "dreb": 2,
      "reb": 3,
      "ast": 7,
      "tov": 5,
      "stl": 2,
      "blk": 0,
      "pf": 2,
      "isStarter": true,
      "detailUrl": "https://www.bleague.jp/roster_detail/?PlayerID=51000382",
      "name": "AI-CHE YU",
      "teamNameRaw": "滋賀レイクス",
      "gameId": "504874",
      "cardPath": "output/Bplayers/B1/251101/game_504874_滋賀レイクス_秋田ノーザンハピネッツ_20251101/滋賀レイクス_7_AI-CHE_YU_20251101.png"
    },
    {
      "no": "17",
      "nameJp": "中山 拓哉",
      "min": "25:36",
      "pts": 10,
      "f2m": 2,
      "f2a": 5,
      "f3m": 2,
      "f3a": 5,
      "ftm": 0,
      "fta": 0,
      "oreb": 3,
      "dreb": 1,
      "reb": 4,
      "ast": 7,
      "tov": 1,
      "stl": 2,
      "blk": 0,
      "pf": 4,
      "isStarter": true,
      "detailUrl": "https://www.bleague.jp/roster_detail/?PlayerID=10848",
      "name": "TAKUYA NAKAYAMA",
      "teamNameRaw": "秋田ノーザンハピネッツ",
      "gameId": "504874",
      "cardPath": "output/Bplayers/B1/251101/game_504874_滋賀レイクス_秋田ノーザンハピネッツ_20251101/秋田ノーザンハピネッツ_17_TAKUYA_NAKAYAMA_20251101.png"
    },
    {
      "teamNameRaw": "宇都宮ブレックス",
      "no": "25",
      "isStarter": true,
      "nameJp": "D.J・ニュービル",
      "detailUrl": "https://www.bleague.jp/roster_detail/?PlayerID=33085",
      "min": "34:25",
      "pts": 31,
      "fg2Str": "5/6",
      "fg2Pct": "83.3",
      "fg3Str": "7/13",
      "fg3Pct": "53.8",
      "ftStr": "0/3",
      "ftPct": "0.0",
      "ptsRatio2P": "32",
      "ptsRatio3P": "68",
      "ptsRatioFT": "0",
      "attRatio2P": "32",
      "attRatio3P": "68",
      "reb": 6,
      "oreb": "0",
      "dreb": "6",
      "ast": 7,
      "stl": "0",
      "blk": "0",
      "to": "2",
      "pf": "2",
      "plusMinus": "11",
      "name": "D.J. NEWBILL",
      "gameId": "504862",
      "cardPath": "output/Bplayers/B1/251101/game_504862_宇都宮ブレックス_ファイティングイーグルス名古屋_20251101/宇都宮ブレックス_25_D.J._NEWBILL_20251101.png"
    },
    {
      "no": "77",
      "nameJp": "岡田 侑大",
      "min": "32:58",
      "pts": 17,
      "f2m": 5,
      "f2a": 9,
      "f3m": 1,
      "f3a": 7,
      "ftm": 4,
      "fta": 6,
      "oreb": 0,
      "dreb": 1,
      "reb": 1,
      "ast": 7,
      "tov": 2,
      "stl": 0,
      "blk": 1,
      "pf": 2,
      "isStarter": true,
      "detailUrl": "https://www.bleague.jp/roster_detail/?PlayerID=18475",
      "name": "YUTA OKADA",
      "teamNameRaw": "島根スサノオマジック",
      "gameId": "504880",
      "cardPath": "output/Bplayers/B1/251101/game_504880_島根スサノオマジック_アルティーリ千葉_20251101/島根スサノオマジック_77_YUTA_OKADA_20251101.png"
    },
    {
      "no": "9",
      "nameJp": "ベンドラメ 礼生",
      "min": "32:04",
      "pts": 8,
      "f2m": 2,
      "f2a": 6,
      "f3m": 1,
      "f3a": 7,
      "ftm": 1,
      "fta": 2,
      "oreb": 0,
      "dreb": 1,
      "reb": 1,
      "ast": 6,
      "tov": 1,
      "stl": 2,
      "blk": 0,
      "pf": 3,
      "isStarter": true,
      "detailUrl": "https://www.bleague.jp/roster_detail/?PlayerID=8447",
      "name": "LEO VENDRAME",
      "teamNameRaw": "サンロッカーズ渋谷",
      "gameId": "504858",
      "cardPath": "output/Bplayers/B1/251101/game_504858_仙台89ERS_サンロッカーズ渋谷_20251101/サンロッカーズ渋谷_9_LEO_VENDRAME_20251101.png"
    },
    {
      "teamNameRaw": "ファイティングイーグルス名古屋",
      "no": "3",
      "isStarter": true,
      "nameJp": "並里 成",
      "detailUrl": "https://www.bleague.jp/roster_detail/?PlayerID=9489",
      "min": "30:12",
      "pts": 15,
      "fg2Str": "4/10",
      "fg2Pct": "40.0",
      "fg3Str": "1/4",
      "fg3Pct": "25.0",
      "ftStr": "4/4",
      "ftPct": "100.0",
      "ptsRatio2P": "53",
      "ptsRatio3P": "20",
      "ptsRatioFT": "27",
      "attRatio2P": "71",
      "attRatio3P": "29",
      "reb": 5,
      "oreb": "1",
      "dreb": "4",
      "ast": 6,
      "stl": "1",
      "blk": "0",
      "to": "0",
      "pf": "1",
      "plusMinus": "-9",
      "name": "NARITO NAMIZATO",
      "gameId": "504862",
      "cardPath": "output/Bplayers/B1/251101/game_504862_宇都宮ブレックス_ファイティングイーグルス名古屋_20251101/ファイティングイーグルス名古屋_3_NARITO_NAMIZATO_20251101.png"
    }
  ]
}