{
  "category": "NBA",
  "date": "20260204",
  "pts": [
    {
      "id": 1630530,
      "no": "25",
      "name": "TREY MURPHY III",
      "teamId": "1610612740",
      "teamNameRaw": "Pelicans",
      "isStarter": true,
      "min": "39:53",
      "pts": 44,
      "reb": 6,
      "oreb": 2,
      "dreb": 4,
      "ast": 6,
      "stl": 3,
      "blk": 0,
      "tov": 4,
      "pf": 1,
      "plusMinus": 3,
      "fg2Pct": "33.3",
      "fg2Str": "3/9",
      "fg3Pct": "63.2",
      "fg3Str": "12/19",
      "ftPct": "100.0",
      "ftStr": "2/2",
      "ptsRatio2P": 14,
      "ptsRatio3P": 82,
      "ptsRatioFT": 5,
      "attRatio2P": 32,
      "attRatio3P": 68,
      "gameId": "0022500729",
      "cardPath": "output/NBAplayers/NBA/260204/game_0022500729_AWAY_HOME_20260204/PELICANS_25_TREY_MURPHY_III_20260204.png",
      "team": "PELICANS"
    },
    {
      "id": 1628973,
      "no": "11",
      "name": "JALEN BRUNSON",
      "teamId": "1610612752",
      "teamNameRaw": "Knicks",
      "isStarter": true,
      "min": "47:00",
      "pts": 42,
      "reb": 8,
      "oreb": 0,
      "dreb": 8,
      "ast": 9,
      "stl": 2,
      "blk": 0,
      "tov": 5,
      "pf": 2,
      "plusMinus": 13,
      "fg2Pct": "60.0",
      "fg2Str": "9/15",
      "fg3Pct": "41.7",
      "fg3Str": "5/12",
      "ftPct": "81.8",
      "ftStr": "9/11",
      "ptsRatio2P": 43,
      "ptsRatio3P": 36,
      "ptsRatioFT": 21,
      "attRatio2P": 56,
      "attRatio3P": 44,
      "gameId": "0022500726",
      "cardPath": "output/NBAplayers/NBA/260204/game_0022500726_AWAY_HOME_20260204/KNICKS_11_JALEN_BRUNSON_20260204.png",
      "team": "KNICKS"
    },
    {
      "id": 1627750,
      "no": "27",
      "name": "JAMAL MURRAY",
      "teamId": "1610612743",
      "teamNameRaw": "Nuggets",
      "isStarter": true,
      "min": "47:45",
      "pts": 39,
      "reb": 5,
      "oreb": 0,
      "dreb": 5,
      "ast": 6,
      "stl": 1,
      "blk": 0,
      "tov": 4,
      "pf": 2,
      "plusMinus": -11,
      "fg2Pct": "63.2",
      "fg2Str": "12/19",
      "fg3Pct": "21.4",
      "fg3Str": "3/14",
      "ftPct": "85.7",
      "ftStr": "6/7",
      "ptsRatio2P": 62,
      "ptsRatio3P": 23,
      "ptsRatioFT": 15,
      "attRatio2P": 58,
      "attRatio3P": 42,
      "gameId": "0022500726",
      "cardPath": "output/NBAplayers/NBA/260204/game_0022500726_AWAY_HOME_20260204/NUGGETS_27_JAMAL_MURRAY_20260204.png",
      "team": "NUGGETS"
    },
    {
      "id": 203999,
      "no": "15",
      "name": "NIKOLA JOKIĆ",
      "teamId": "1610612743",
      "teamNameRaw": "Nuggets",
      "isStarter": true,
      "min": "44:36",
      "pts": 30,
      "reb": 14,
      "oreb": 7,
      "dreb": 7,
      "ast": 10,
      "stl": 0,
      "blk": 0,
      "tov": 0,
      "pf": 4,
      "plusMinus": 3,
      "fg2Pct": "64.3",
      "fg2Str": "9/14",
      "fg3Pct": "7.7",
      "fg3Str": "1/13",
      "ftPct": "75.0",
      "ftStr": "9/12",
      "ptsRatio2P": 60,
      "ptsRatio3P": 10,
      "ptsRatioFT": 30,
      "attRatio2P": 52,
      "attRatio3P": 48,
      "gameId": "0022500726",
      "cardPath": "output/NBAplayers/NBA/260204/game_0022500726_AWAY_HOME_20260204/NUGGETS_15_NIKOLA_JOKIĆ_20260204.png",
      "team": "NUGGETS"
    },
    {
      "id": 1630162,
      "no": "5",
      "name": "ANTHONY EDWARDS",
      "teamId": "1610612750",
      "teamNameRaw": "Timberwolves",
      "isStarter": true,
      "min": "37:46",
      "pts": 30,
      "reb": 8,
      "oreb": 0,
      "dreb": 8,
      "ast": 5,
      "stl": 3,
      "blk": 1,
      "tov": 2,
      "pf": 1,
      "plusMinus": -2,
      "fg2Pct": "66.7",
      "fg2Str": "10/15",
      "fg3Pct": "12.5",
      "fg3Str": "1/8",
      "ftPct": "70.0",
      "ftStr": "7/10",
      "ptsRatio2P": 67,
      "ptsRatio3P": 10,
      "ptsRatioFT": 23,
      "attRatio2P": 65,
      "attRatio3P": 35,
      "gameId": "0022500727",
      "cardPath": "output/NBAplayers/NBA/260204/game_0022500727_AWAY_HOME_20260204/TIMBERWOLVES_5_ANTHONY_EDWARDS_20260204.png",
      "team": "TIMBERWOLVES"
    },
    {
      "id": 1628378,
      "no": "45",
      "name": "DONOVAN MITCHELL",
      "teamId": "1610612739",
      "teamNameRaw": "Cavaliers",
      "isStarter": true,
      "min": "30:05",
      "pts": 29,
      "reb": 5,
      "oreb": 0,
      "dreb": 5,
      "ast": 9,
      "stl": 4,
      "blk": 0,
      "tov": 2,
      "pf": 1,
      "plusMinus": 24,
      "fg2Pct": "70.0",
      "fg2Str": "7/10",
      "fg3Pct": "33.3",
      "fg3Str": "3/9",
      "ftPct": "100.0",
      "ftStr": "6/6",
      "ptsRatio2P": 48,
      "ptsRatio3P": 31,
      "ptsRatioFT": 21,
      "attRatio2P": 53,
      "attRatio3P": 47,
      "gameId": "0022500732",
      "cardPath": "output/NBAplayers/NBA/260204/game_0022500732_AWAY_HOME_20260204/CAVALIERS_45_DONOVAN_MITCHELL_20260204.png",
      "team": "CAVALIERS"
    },
    {
      "id": 1628401,
      "no": "9",
      "name": "DERRICK WHITE",
      "teamId": "1610612738",
      "teamNameRaw": "Celtics",
      "isStarter": true,
      "min": "37:06",
      "pts": 28,
      "reb": 1,
      "oreb": 0,
      "dreb": 1,
      "ast": 8,
      "stl": 0,
      "blk": 0,
      "tov": 2,
      "pf": 3,
      "plusMinus": 15,
      "fg2Pct": "36.4",
      "fg2Str": "4/11",
      "fg3Pct": "42.9",
      "fg3Str": "6/14",
      "ftPct": "100.0",
      "ftStr": "2/2",
      "ptsRatio2P": 29,
      "ptsRatio3P": 64,
      "ptsRatioFT": 7,
      "attRatio2P": 44,
      "attRatio3P": 56,
      "gameId": "0022500728",
      "cardPath": "output/NBAplayers/NBA/260204/game_0022500728_AWAY_HOME_20260204/CELTICS_9_DERRICK_WHITE_20260204.png",
      "team": "CELTICS"
    },
    {
      "id": 1629660,
      "no": "2",
      "name": "TY JEROME",
      "teamId": "1610612763",
      "teamNameRaw": "Grizzlies",
      "isStarter": true,
      "min": "20:41",
      "pts": 28,
      "reb": 1,
      "oreb": 1,
      "dreb": 0,
      "ast": 7,
      "stl": 1,
      "blk": 0,
      "tov": 0,
      "pf": 2,
      "plusMinus": 9,
      "fg2Pct": "70.0",
      "fg2Str": "7/10",
      "fg3Pct": "75.0",
      "fg3Str": "3/4",
      "ftPct": "83.3",
      "ftStr": "5/6",
      "ptsRatio2P": 50,
      "ptsRatio3P": 32,
      "ptsRatioFT": 18,
      "attRatio2P": 71,
      "attRatio3P": 29,
      "gameId": "0022500731",
      "cardPath": "output/NBAplayers/NBA/260204/game_0022500731_AWAY_HOME_20260204/GRIZZLIES_2_TY_JEROME_20260204.png",
      "team": "GRIZZLIES"
    },
    {
      "id": 1630202,
      "no": "11",
      "name": "PAYTON PRITCHARD",
      "teamId": "1610612738",
      "teamNameRaw": "Celtics",
      "isStarter": false,
      "min": "33:29",
      "pts": 27,
      "reb": 3,
      "oreb": 1,
      "dreb": 2,
      "ast": 7,
      "stl": 0,
      "blk": 0,
      "tov": 1,
      "pf": 0,
      "plusMinus": 17,
      "fg2Pct": "40.0",
      "fg2Str": "4/10",
      "fg3Pct": "50.0",
      "fg3Str": "5/10",
      "ftPct": "80.0",
      "ftStr": "4/5",
      "ptsRatio2P": 30,
      "ptsRatio3P": 56,
      "ptsRatioFT": 15,
      "attRatio2P": 50,
      "attRatio3P": 50,
      "gameId": "0022500728",
      "cardPath": "output/NBAplayers/NBA/260204/game_0022500728_AWAY_HOME_20260204/CELTICS_11_PAYTON_PRITCHARD_20260204.png",
      "team": "CELTICS"
    },
    {
      "id": 1631157,
      "no": "13",
      "name": "RYAN ROLLINS",
      "teamId": "1610612749",
      "teamNameRaw": "Bucks",
      "isStarter": true,
      "min": "39:48",
      "pts": 27,
      "reb": 4,
      "oreb": 0,
      "dreb": 4,
      "ast": 4,
      "stl": 0,
      "blk": 0,
      "tov": 4,
      "pf": 2,
      "plusMinus": 9,
      "fg2Pct": "77.8",
      "fg2Str": "7/9",
      "fg3Pct": "30.0",
      "fg3Str": "3/10",
      "ftPct": "80.0",
      "ftStr": "4/5",
      "ptsRatio2P": 52,
      "ptsRatio3P": 33,
      "ptsRatioFT": 15,
      "attRatio2P": 47,
      "attRatio3P": 53,
      "gameId": "0022500729",
      "cardPath": "output/NBAplayers/NBA/260204/game_0022500729_AWAY_HOME_20260204/BUCKS_13_RYAN_ROLLINS_20260204.png",
      "team": "BUCKS"
    }
  ],
  "reb": [
    {
      "id": 1629674,
      "no": "88",
      "name": "NEEMIAS QUETA",
      "teamId": "1610612738",
      "teamNameRaw": "Celtics",
      "isStarter": true,
      "min": "38:55",
      "pts": 10,
      "reb": 19,
      "oreb": 7,
      "dreb": 12,
      "ast": 2,
      "stl": 2,
      "blk": 5,
      "tov": 2,
      "pf": 2,
      "plusMinus": 22,
      "fg2Pct": "75.0",
      "fg2Str": "3/4",
      "fg3Pct": "0.0",
      "fg3Str": "0/0",
      "ftPct": "100.0",
      "ftStr": "4/4",
      "ptsRatio2P": 60,
      "ptsRatio3P": 0,
      "ptsRatioFT": 40,
      "attRatio2P": 100,
      "attRatio3P": 0,
      "gameId": "0022500728",
      "cardPath": "output/NBAplayers/NBA/260204/game_0022500728_AWAY_HOME_20260204/CELTICS_88_NEEMIAS_QUETA_20260204.png",
      "team": "CELTICS"
    },
    {
      "id": 1628436,
      "no": "7",
      "name": "LUKE KORNET",
      "teamId": "1610612759",
      "teamNameRaw": "Spurs",
      "isStarter": false,
      "min": "15:08",
      "pts": 4,
      "reb": 15,
      "oreb": 9,
      "dreb": 6,
      "ast": 2,
      "stl": 1,
      "blk": 0,
      "tov": 0,
      "pf": 0,
      "plusMinus": -4,
      "fg2Pct": "28.6",
      "fg2Str": "2/7",
      "fg3Pct": "0.0",
      "fg3Str": "0/0",
      "ftPct": "0.0",
      "ftStr": "0/0",
      "ptsRatio2P": 100,
      "ptsRatio3P": 0,
      "ptsRatioFT": 0,
      "attRatio2P": 100,
      "attRatio3P": 0,
      "gameId": "0022500730",
      "cardPath": "output/NBAplayers/NBA/260204/game_0022500730_AWAY_HOME_20260204/SPURS_7_LUKE_KORNET_20260204.png",
      "team": "SPURS"
    },
    {
      "id": 1627734,
      "no": "11",
      "name": "DOMANTAS SABONIS",
      "teamId": "1610612758",
      "teamNameRaw": "Kings",
      "isStarter": true,
      "min": "24:04",
      "pts": 24,
      "reb": 15,
      "oreb": 7,
      "dreb": 8,
      "ast": 3,
      "stl": 1,
      "blk": 0,
      "tov": 1,
      "pf": 3,
      "plusMinus": -12,
      "fg2Pct": "55.6",
      "fg2Str": "10/18",
      "fg3Pct": "0.0",
      "fg3Str": "0/0",
      "ftPct": "100.0",
      "ftStr": "4/4",
      "ptsRatio2P": 83,
      "ptsRatio3P": 0,
      "ptsRatioFT": 17,
      "attRatio2P": 100,
      "attRatio3P": 0,
      "gameId": "0022500731",
      "cardPath": "output/NBAplayers/NBA/260204/game_0022500731_AWAY_HOME_20260204/KINGS_11_DOMANTAS_SABONIS_20260204.png",
      "team": "KINGS"
    },
    {
      "id": 203999,
      "no": "15",
      "name": "NIKOLA JOKIĆ",
      "teamId": "1610612743",
      "teamNameRaw": "Nuggets",
      "isStarter": true,
      "min": "44:36",
      "pts": 30,
      "reb": 14,
      "oreb": 7,
      "dreb": 7,
      "ast": 10,
      "stl": 0,
      "blk": 0,
      "tov": 0,
      "pf": 4,
      "plusMinus": 3,
      "fg2Pct": "64.3",
      "fg2Str": "9/14",
      "fg3Pct": "7.7",
      "fg3Str": "1/13",
      "ftPct": "75.0",
      "ftStr": "9/12",
      "ptsRatio2P": 60,
      "ptsRatio3P": 10,
      "ptsRatioFT": 30,
      "attRatio2P": 52,
      "attRatio3P": 48,
      "gameId": "0022500726",
      "cardPath": "output/NBAplayers/NBA/260204/game_0022500726_AWAY_HOME_20260204/NUGGETS_15_NIKOLA_JOKIĆ_20260204.png",
      "team": "NUGGETS"
    },
    {
      "id": 1641705,
      "no": "1",
      "name": "VICTOR WEMBANYAMA",
      "teamId": "1610612759",
      "teamNameRaw": "Spurs",
      "isStarter": true,
      "min": "28:21",
      "pts": 22,
      "reb": 14,
      "oreb": 3,
      "dreb": 11,
      "ast": 2,
      "stl": 0,
      "blk": 2,
      "tov": 2,
      "pf": 1,
      "plusMinus": 17,
      "fg2Pct": "57.1",
      "fg2Str": "8/14",
      "fg3Pct": "50.0",
      "fg3Str": "1/2",
      "ftPct": "37.5",
      "ftStr": "3/8",
      "ptsRatio2P": 73,
      "ptsRatio3P": 14,
      "ptsRatioFT": 14,
      "attRatio2P": 88,
      "attRatio3P": 13,
      "gameId": "0022500730",
      "cardPath": "output/NBAplayers/NBA/260204/game_0022500730_AWAY_HOME_20260204/SPURS_1_VICTOR_WEMBANYAMA_20260204.png",
      "team": "SPURS"
    },
    {
      "id": 1626157,
      "no": "32",
      "name": "KARL-ANTHONY TOWNS",
      "teamId": "1610612752",
      "teamNameRaw": "Knicks",
      "isStarter": true,
      "min": "31:00",
      "pts": 24,
      "reb": 12,
      "oreb": 3,
      "dreb": 9,
      "ast": 1,
      "stl": 0,
      "blk": 0,
      "tov": 1,
      "pf": 6,
      "plusMinus": 12,
      "fg2Pct": "100.0",
      "fg2Str": "7/7",
      "fg3Pct": "33.3",
      "fg3Str": "2/6",
      "ftPct": "100.0",
      "ftStr": "4/4",
      "ptsRatio2P": 58,
      "ptsRatio3P": 25,
      "ptsRatioFT": 17,
      "attRatio2P": 54,
      "attRatio3P": 46,
      "gameId": "0022500726",
      "cardPath": "output/NBAplayers/NBA/260204/game_0022500726_AWAY_HOME_20260204/KNICKS_32_KARL-ANTHONY_TOWNS_20260204.png",
      "team": "KNICKS"
    },
    {
      "id": 203497,
      "no": "27",
      "name": "RUDY GOBERT",
      "teamId": "1610612750",
      "teamNameRaw": "Timberwolves",
      "isStarter": true,
      "min": "32:53",
      "pts": 10,
      "reb": 12,
      "oreb": 2,
      "dreb": 10,
      "ast": 2,
      "stl": 1,
      "blk": 1,
      "tov": 0,
      "pf": 3,
      "plusMinus": 11,
      "fg2Pct": "100.0",
      "fg2Str": "4/4",
      "fg3Pct": "0.0",
      "fg3Str": "0/0",
      "ftPct": "40.0",
      "ftStr": "2/5",
      "ptsRatio2P": 80,
      "ptsRatio3P": 0,
      "ptsRatioFT": 20,
      "attRatio2P": 100,
      "attRatio3P": 0,
      "gameId": "0022500727",
      "cardPath": "output/NBAplayers/NBA/260204/game_0022500727_AWAY_HOME_20260204/TIMBERWOLVES_27_RUDY_GOBERT_20260204.png",
      "team": "TIMBERWOLVES"
    },
    {
      "id": 1631119,
      "no": "6",
      "name": "JAYLIN WILLIAMS",
      "teamId": "1610612760",
      "teamNameRaw": "Thunder",
      "isStarter": true,
      "min": "39:40",
      "pts": 24,
      "reb": 12,
      "oreb": 0,
      "dreb": 12,
      "ast": 4,
      "stl": 0,
      "blk": 2,
      "tov": 2,
      "pf": 4,
      "plusMinus": -14,
      "fg2Pct": "50.0",
      "fg2Str": "2/4",
      "fg3Pct": "36.4",
      "fg3Str": "4/11",
      "ftPct": "100.0",
      "ftStr": "8/8",
      "ptsRatio2P": 17,
      "ptsRatio3P": 50,
      "ptsRatioFT": 33,
      "attRatio2P": 27,
      "attRatio3P": 73,
      "gameId": "0022500730",
      "cardPath": "output/NBAplayers/NBA/260204/game_0022500730_AWAY_HOME_20260204/THUNDER_6_JAYLIN_WILLIAMS_20260204.png",
      "team": "THUNDER"
    },
    {
      "id": 1642928,
      "no": "32",
      "name": "DYLAN CARDWELL",
      "teamId": "1610612758",
      "teamNameRaw": "Kings",
      "isStarter": false,
      "min": "25:49",
      "pts": 5,
      "reb": 11,
      "oreb": 4,
      "dreb": 7,
      "ast": 1,
      "stl": 0,
      "blk": 1,
      "tov": 0,
      "pf": 3,
      "plusMinus": 9,
      "fg2Pct": "50.0",
      "fg2Str": "1/2",
      "fg3Pct": "0.0",
      "fg3Str": "0/0",
      "ftPct": "75.0",
      "ftStr": "3/4",
      "ptsRatio2P": 40,
      "ptsRatio3P": 0,
      "ptsRatioFT": 60,
      "attRatio2P": 100,
      "attRatio3P": 0,
      "gameId": "0022500731",
      "cardPath": "output/NBAplayers/NBA/260204/game_0022500731_AWAY_HOME_20260204/KINGS_32_DYLAN_CARDWELL_20260204.png",
      "team": "KINGS"
    },
    {
      "id": 1628386,
      "no": "31",
      "name": "JARRETT ALLEN",
      "teamId": "1610612739",
      "teamNameRaw": "Cavaliers",
      "isStarter": true,
      "min": "23:23",
      "pts": 10,
      "reb": 11,
      "oreb": 3,
      "dreb": 8,
      "ast": 3,
      "stl": 2,
      "blk": 1,
      "tov": 0,
      "pf": 0,
      "plusMinus": 20,
      "fg2Pct": "62.5",
      "fg2Str": "5/8",
      "fg3Pct": "0.0",
      "fg3Str": "0/0",
      "ftPct": "0.0",
      "ftStr": "0/2",
      "ptsRatio2P": 100,
      "ptsRatio3P": 0,
      "ptsRatioFT": 0,
      "attRatio2P": 100,
      "attRatio3P": 0,
      "gameId": "0022500732",
      "cardPath": "output/NBAplayers/NBA/260204/game_0022500732_AWAY_HOME_20260204/CAVALIERS_31_JARRETT_ALLEN_20260204.png",
      "team": "CAVALIERS"
    }
  ],
  "ast": [
    {
      "id": 203999,
      "no": "15",
      "name": "NIKOLA JOKIĆ",
      "teamId": "1610612743",
      "teamNameRaw": "Nuggets",
      "isStarter": true,
      "min": "44:36",
      "pts": 30,
      "reb": 14,
      "oreb": 7,
      "dreb": 7,
      "ast": 10,
      "stl": 0,
      "blk": 0,
      "tov": 0,
      "pf": 4,
      "plusMinus": 3,
      "fg2Pct": "64.3",
      "fg2Str": "9/14",
      "fg3Pct": "7.7",
      "fg3Str": "1/13",
      "ftPct": "75.0",
      "ftStr": "9/12",
      "ptsRatio2P": 60,
      "ptsRatio3P": 10,
      "ptsRatioFT": 30,
      "attRatio2P": 52,
      "attRatio3P": 48,
      "gameId": "0022500726",
      "cardPath": "output/NBAplayers/NBA/260204/game_0022500726_AWAY_HOME_20260204/NUGGETS_15_NIKOLA_JOKIĆ_20260204.png",
      "team": "NUGGETS"
    },
    {
      "id": 1628368,
      "no": "4",
      "name": "DE'AARON FOX",
      "teamId": "1610612759",
      "teamNameRaw": "Spurs",
      "isStarter": true,
      "min": "33:13",
      "pts": 15,
      "reb": 4,
      "oreb": 0,
      "dreb": 4,
      "ast": 10,
      "stl": 3,
      "blk": 1,
      "tov": 1,
      "pf": 1,
      "plusMinus": 20,
      "fg2Pct": "71.4",
      "fg2Str": "5/7",
      "fg3Pct": "0.0",
      "fg3Str": "0/3",
      "ftPct": "83.3",
      "ftStr": "5/6",
      "ptsRatio2P": 67,
      "ptsRatio3P": 0,
      "ptsRatioFT": 33,
      "attRatio2P": 70,
      "attRatio3P": 30,
      "gameId": "0022500730",
      "cardPath": "output/NBAplayers/NBA/260204/game_0022500730_AWAY_HOME_20260204/SPURS_4_DEAARON_FOX_20260204.png",
      "team": "SPURS"
    },
    {
      "id": 1628973,
      "no": "11",
      "name": "JALEN BRUNSON",
      "teamId": "1610612752",
      "teamNameRaw": "Knicks",
      "isStarter": true,
      "min": "47:00",
      "pts": 42,
      "reb": 8,
      "oreb": 0,
      "dreb": 8,
      "ast": 9,
      "stl": 2,
      "blk": 0,
      "tov": 5,
      "pf": 2,
      "plusMinus": 13,
      "fg2Pct": "60.0",
      "fg2Str": "9/15",
      "fg3Pct": "41.7",
      "fg3Str": "5/12",
      "ftPct": "81.8",
      "ftStr": "9/11",
      "ptsRatio2P": 43,
      "ptsRatio3P": 36,
      "ptsRatioFT": 21,
      "attRatio2P": 56,
      "attRatio3P": 44,
      "gameId": "0022500726",
      "cardPath": "output/NBAplayers/NBA/260204/game_0022500726_AWAY_HOME_20260204/KNICKS_11_JALEN_BRUNSON_20260204.png",
      "team": "KNICKS"
    },
    {
      "id": 1628398,
      "no": "18",
      "name": "KYLE KUZMA",
      "teamId": "1610612749",
      "teamNameRaw": "Bucks",
      "isStarter": true,
      "min": "30:59",
      "pts": 7,
      "reb": 6,
      "oreb": 0,
      "dreb": 6,
      "ast": 9,
      "stl": 0,
      "blk": 0,
      "tov": 3,
      "pf": 1,
      "plusMinus": -2,
      "fg2Pct": "66.7",
      "fg2Str": "2/3",
      "fg3Pct": "50.0",
      "fg3Str": "1/2",
      "ftPct": "0.0",
      "ftStr": "0/0",
      "ptsRatio2P": 57,
      "ptsRatio3P": 43,
      "ptsRatioFT": 0,
      "attRatio2P": 60,
      "attRatio3P": 40,
      "gameId": "0022500729",
      "cardPath": "output/NBAplayers/NBA/260204/game_0022500729_AWAY_HOME_20260204/BUCKS_18_KYLE_KUZMA_20260204.png",
      "team": "BUCKS"
    },
    {
      "id": 1629645,
      "no": "7",
      "name": "KEVIN PORTER JR.",
      "teamId": "1610612749",
      "teamNameRaw": "Bucks",
      "isStarter": false,
      "min": "29:23",
      "pts": 18,
      "reb": 6,
      "oreb": 1,
      "dreb": 5,
      "ast": 9,
      "stl": 5,
      "blk": 0,
      "tov": 4,
      "pf": 2,
      "plusMinus": 1,
      "fg2Pct": "63.6",
      "fg2Str": "7/11",
      "fg3Pct": "0.0",
      "fg3Str": "0/3",
      "ftPct": "100.0",
      "ftStr": "4/4",
      "ptsRatio2P": 78,
      "ptsRatio3P": 0,
      "ptsRatioFT": 22,
      "attRatio2P": 79,
      "attRatio3P": 21,
      "gameId": "0022500729",
      "cardPath": "output/NBAplayers/NBA/260204/game_0022500729_AWAY_HOME_20260204/BUCKS_7_KEVIN_PORTER_JR._20260204.png",
      "team": "BUCKS"
    },
    {
      "id": 1628378,
      "no": "45",
      "name": "DONOVAN MITCHELL",
      "teamId": "1610612739",
      "teamNameRaw": "Cavaliers",
      "isStarter": true,
      "min": "30:05",
      "pts": 29,
      "reb": 5,
      "oreb": 0,
      "dreb": 5,
      "ast": 9,
      "stl": 4,
      "blk": 0,
      "tov": 2,
      "pf": 1,
      "plusMinus": 24,
      "fg2Pct": "70.0",
      "fg2Str": "7/10",
      "fg3Pct": "33.3",
      "fg3Str": "3/9",
      "ftPct": "100.0",
      "ftStr": "6/6",
      "ptsRatio2P": 48,
      "ptsRatio3P": 31,
      "ptsRatioFT": 21,
      "attRatio2P": 53,
      "attRatio3P": 47,
      "gameId": "0022500732",
      "cardPath": "output/NBAplayers/NBA/260204/game_0022500732_AWAY_HOME_20260204/CAVALIERS_45_DONOVAN_MITCHELL_20260204.png",
      "team": "CAVALIERS"
    },
    {
      "id": 1630567,
      "no": "4",
      "name": "SCOTTIE BARNES",
      "teamId": "1610612761",
      "teamNameRaw": "Raptors",
      "isStarter": true,
      "min": "36:37",
      "pts": 22,
      "reb": 10,
      "oreb": 1,
      "dreb": 9,
      "ast": 8,
      "stl": 1,
      "blk": 1,
      "tov": 3,
      "pf": 2,
      "plusMinus": 9,
      "fg2Pct": "72.7",
      "fg2Str": "8/11",
      "fg3Pct": "0.0",
      "fg3Str": "0/0",
      "ftPct": "75.0",
      "ftStr": "6/8",
      "ptsRatio2P": 73,
      "ptsRatio3P": 0,
      "ptsRatioFT": 27,
      "attRatio2P": 100,
      "attRatio3P": 0,
      "gameId": "0022500727",
      "cardPath": "output/NBAplayers/NBA/260204/game_0022500727_AWAY_HOME_20260204/RAPTORS_4_SCOTTIE_BARNES_20260204.png",
      "team": "RAPTORS"
    },
    {
      "id": 1630193,
      "no": "5",
      "name": "IMMANUEL QUICKLEY",
      "teamId": "1610612761",
      "teamNameRaw": "Raptors",
      "isStarter": true,
      "min": "33:36",
      "pts": 23,
      "reb": 5,
      "oreb": 0,
      "dreb": 5,
      "ast": 8,
      "stl": 1,
      "blk": 0,
      "tov": 2,
      "pf": 1,
      "plusMinus": 2,
      "fg2Pct": "50.0",
      "fg2Str": "2/4",
      "fg3Pct": "75.0",
      "fg3Str": "6/8",
      "ftPct": "50.0",
      "ftStr": "1/2",
      "ptsRatio2P": 17,
      "ptsRatio3P": 78,
      "ptsRatioFT": 4,
      "attRatio2P": 33,
      "attRatio3P": 67,
      "gameId": "0022500727",
      "cardPath": "output/NBAplayers/NBA/260204/game_0022500727_AWAY_HOME_20260204/RAPTORS_5_IMMANUEL_QUICKLEY_20260204.png",
      "team": "RAPTORS"
    },
    {
      "id": 1628401,
      "no": "9",
      "name": "DERRICK WHITE",
      "teamId": "1610612738",
      "teamNameRaw": "Celtics",
      "isStarter": true,
      "min": "37:06",
      "pts": 28,
      "reb": 1,
      "oreb": 0,
      "dreb": 1,
      "ast": 8,
      "stl": 0,
      "blk": 0,
      "tov": 2,
      "pf": 3,
      "plusMinus": 15,
      "fg2Pct": "36.4",
      "fg2Str": "4/11",
      "fg3Pct": "42.9",
      "fg3Str": "6/14",
      "ftPct": "100.0",
      "ftStr": "2/2",
      "ptsRatio2P": 29,
      "ptsRatio3P": 64,
      "ptsRatioFT": 7,
      "attRatio2P": 44,
      "attRatio3P": 56,
      "gameId": "0022500728",
      "cardPath": "output/NBAplayers/NBA/260204/game_0022500728_AWAY_HOME_20260204/CELTICS_9_DERRICK_WHITE_20260204.png",
      "team": "CELTICS"
    },
    {
      "id": 1629627,
      "no": "1",
      "name": "ZION WILLIAMSON",
      "teamId": "1610612740",
      "teamNameRaw": "Pelicans",
      "isStarter": true,
      "min": "37:43",
      "pts": 20,
      "reb": 5,
      "oreb": 0,
      "dreb": 5,
      "ast": 8,
      "stl": 2,
      "blk": 0,
      "tov": 2,
      "pf": 5,
      "plusMinus": -1,
      "fg2Pct": "45.5",
      "fg2Str": "5/11",
      "fg3Pct": "0.0",
      "fg3Str": "0/0",
      "ftPct": "83.3",
      "ftStr": "10/12",
      "ptsRatio2P": 50,
      "ptsRatio3P": 0,
      "ptsRatioFT": 50,
      "attRatio2P": 100,
      "attRatio3P": 0,
      "gameId": "0022500729",
      "cardPath": "output/NBAplayers/NBA/260204/game_0022500729_AWAY_HOME_20260204/PELICANS_1_ZION_WILLIAMSON_20260204.png",
      "team": "PELICANS"
    }
  ]
}